seqera_ai/__init__.py
seqera_ai/__main__.py
seqera_ai/approval.py
seqera_ai/auth.py
seqera_ai/cli.py
seqera_ai/nextflow_schema.json
seqera_ai/render.py
seqera_ai/schema_documentation.md
seqera-0.2.11.dist-info/METADATA
seqera-0.2.11.dist-info/WHEEL
seqera-0.2.11.dist-info/entry_points.txt
seqera-0.2.11.dist-info/licenses/LICENSE
seqera-0.2.11.dist-info/RECORD
