Metadata-Version: 2.4
Name: seqera
Version: 0.2.11
Summary: Seqera AI CLI – terminal assistant for Nextflow, bioinformatics, and workflow management
Project-URL: Homepage, https://docs.seqera.io/platform-cloud/seqera-ai
Project-URL: Issues, https://feedback.seqera.io/seqera-ai-feature-requests
Project-URL: Documentation, https://docs.seqera.io/platform-cloud/seqera-ai
Project-URL: Changelog, https://docs.seqera.io/changelog/tags/seqera-cloud
Project-URL: Twitter, https://x.com/SeqeraLabs
Author-email: Seqera <support@seqera.io>
License: Custom
License-File: LICENSE
Keywords: ai assistant,ai ide,bioinformatics,nextflow,workflows
Requires-Python: >=3.13
Requires-Dist: click>=8.1.3
Requires-Dist: keyring>=24.3.0
Requires-Dist: mcp>=1.0.0
Requires-Dist: prompt-toolkit>=3.0.0
Requires-Dist: python-dotenv>=1.0.0
Requires-Dist: requests>=2.32.0
Requires-Dist: rich>=13.7.0
Requires-Dist: websocket-client>=1.7.0
